hj_check_os_version-0.4.1.dist-info/METADATA
hj_check_os_version-0.4.1.dist-info/WHEEL
hj_check_os_version-0.4.1.dist-info/entry_points.txt
hj_check_os_version/__init__.py
hj_check_os_version/hi.py
hj_check_os_version/osver.py
hj_check_os_version-0.4.1.dist-info/RECORD
