Metadata-Version: 2.1
Name: hj-check-os-version
Version: 0.4.1
Summary: Default template for PDM package
Author-Email: heejin131 <journeyjean131@gmail.com>
License: MIT
Project-URL: Homepage, https://github.com/heejin131/hj-check-os-version
Project-URL: Issues, https://github.com/heejin131/hj-check-os-version/issues
Requires-Python: >=3.10
Requires-Dist: stundrg-check-os-ver>=0.2.3
Requires-Dist: ppabam-check-os-ver>=0.2.0
Requires-Dist: check-os-ver>=0.2.1
Requires-Dist: jacob-os-version-check>=0.2.4
Requires-Dist: cho-check-os-ver>=0.2.3
Requires-Dist: nunininu-check-os-ver>=0.3.0
Requires-Dist: seo-check-os-version>=0.2.0
Requires-Dist: lucas-check-os-ver>=0.2.1
